umapi_client/__init__.py
umapi_client/api.py
umapi_client/auth.py
umapi_client/connection.py
umapi_client/error.py
umapi_client/functional.py
umapi_client/version.py
umapi_client-3.0.1.dist-info/LICENSE
umapi_client-3.0.1.dist-info/WHEEL
umapi_client-3.0.1.dist-info/METADATA
umapi_client-3.0.1.dist-info/RECORD
