Metadata-Version: 2.1
Name: umapi-client
Version: 3.0.1
Summary: Client for the User Management API (UMAPI) from Adobe - see https://adobe.ly/2h1pHgV
Home-page: https://github.com/adobe-apiplatform/umapi-client.py/
License: MIT
Author: Andrew Dorton
Author-email: adorton@adobe.com
Maintainer: Andrew Dorton
Maintainer-email: adorton@adobe.com
Requires-Python: >=3.6,<4.0
Classifier: Development Status :: 5 - Production/Stable
Classifier: Intended Audience :: Developers
Classifier: Intended Audience :: System Administrators
Classifier: License :: OSI Approved :: MIT License
Classifier: Programming Language :: Python :: 3
Classifier: Programming Language :: Python :: 3.6
Classifier: Programming Language :: Python :: 3.7
Classifier: Programming Language :: Python :: 3.8
Classifier: Programming Language :: Python :: 3.9
Classifier: Programming Language :: Python :: 3.10
Classifier: Programming Language :: Python :: 3.11
Classifier: Programming Language :: Python :: 3.10
Classifier: Programming Language :: Python :: 3.6
Classifier: Programming Language :: Python :: 3.7
Classifier: Programming Language :: Python :: 3.8
Classifier: Programming Language :: Python :: 3.9
Requires-Dist: PyJWT (==2.4.0)
Requires-Dist: cryptography (>=38.0.4,<39.0.0)
Requires-Dist: requests (>=2.25.1,<3.0.0)
Project-URL: Documentation, https://adobe-apiplatform.github.io/umapi-client.py/
